playcli/__init__.py
playcli/__main__.py
playcli/cli.py
playcli/core/__init__.py
playcli/core/commands/__init__.py
playcli/core/commands/credits.py
playcli/core/commands/download.py
playcli/core/commands/search.py
playcli/core/platforms/__init__.py
playcli/core/platforms/elamigos.py
playcli/core/platforms/steamunlocked.py
playcli/core/web.py
playcli/main.py
playcli/models/__init__.py
playcli/models/driver.py
playcli/models/platforms.py
playcli-0.3.1.dist-info/entry_points.txt
playcli-0.3.1.dist-info/METADATA
playcli-0.3.1.dist-info/WHEEL
playcli-0.3.1.dist-info/RECORD
